chess_minimax/Board.py
chess_minimax/ChessPiece.py
chess_minimax/Computer.py
chess_minimax/Logger.py
chess_minimax/__init__.py
chess_minimax/assets/JohnPablok Cburnett Chess set/128px/b_bishop_png_shadow_128px.png
chess_minimax/assets/JohnPablok Cburnett Chess set/128px/b_king_png_shadow_128px.png
chess_minimax/assets/JohnPablok Cburnett Chess set/128px/b_knight_png_shadow_128px.png
chess_minimax/assets/JohnPablok Cburnett Chess set/128px/b_pawn_png_shadow_128px.png
chess_minimax/assets/JohnPablok Cburnett Chess set/128px/b_queen_png_shadow_128px.png
chess_minimax/assets/JohnPablok Cburnett Chess set/128px/b_rook_png_shadow_128px.png
chess_minimax/assets/JohnPablok Cburnett Chess set/128px/highlight_128px.png
chess_minimax/assets/JohnPablok Cburnett Chess set/128px/square brown dark_png_shadow_128px.png
chess_minimax/assets/JohnPablok Cburnett Chess set/128px/square brown light_png_shadow_128px.png
chess_minimax/assets/JohnPablok Cburnett Chess set/128px/square gray dark _png_shadow_128px.png
chess_minimax/assets/JohnPablok Cburnett Chess set/128px/square gray light _png_shadow_128px.png
chess_minimax/assets/JohnPablok Cburnett Chess set/128px/w_bishop_png_shadow_128px.png
chess_minimax/assets/JohnPablok Cburnett Chess set/128px/w_king_png_shadow_128px.png
chess_minimax/assets/JohnPablok Cburnett Chess set/128px/w_knight_png_shadow_128px.png
chess_minimax/assets/JohnPablok Cburnett Chess set/128px/w_pawn_png_shadow_128px.png
chess_minimax/assets/JohnPablok Cburnett Chess set/128px/w_queen_png_shadow_128px.png
chess_minimax/assets/JohnPablok Cburnett Chess set/128px/w_rook_png_shadow_128px.png
chess_minimax/assets/icon.png
chess_minimax/graphics.py
chess_minimax/main.py
chess_minimax-0.1.8.dist-info/WHEEL
chess_minimax-0.1.8.dist-info/entry_points.txt
chess_minimax-0.1.8.dist-info/METADATA
chess_minimax-0.1.8.dist-info/RECORD
