Metadata-Version: 2.3
Name: chess-minimax
Version: 0.1.8
Summary: A pure Python chess AI (minimax algorithm) integrated with a PyGame to interact with a chess board.
Author: hobs
Author-email: hobs <git@totalgood.com>
Requires-Dist: pygame>=2.6.1
Requires-Python: >=3.10
